components/Stack.v
module Stack #(
    parameter DEPTH = 127,  //? Number of stack elements.
    parameter WIDTH = 31    //? Width of a stack element.
) (
    input clk,
    input push,  //? Push signal. Takes priority over pop signal.
    input [WIDTH:0] push_data,
    input [2:0] pop,  //? Pop amount. Supports popping up to 8 elements per clock cycle.
    output [WIDTH:0] preview0,  //? Preview the top element of the stack.
    output [WIDTH:0] preview1  //? Preview the second top element of the stack.
);
    // stack_ptr points to the next free stack index.
    reg [$clog2(DEPTH):0] stack_ptr = 0;
    reg [WIDTH:0] stack[DEPTH:0];

    // Update the stack based on push or pop signals.
    always @(posedge clk) begin
        if ((push == 1) && (stack_ptr < DEPTH)) begin  // TODO: Handle overflow
            stack[stack_ptr] <= push_data;
            stack_ptr <= stack_ptr + 1;
        end else if (stack_ptr >= pop) begin  // TODO: Handle underflow
            stack_ptr <= stack_ptr - pop;
        end
    end

    // Assign the top two elements of the stack to the preview outputs
    assign preview0 = (stack_ptr > 0) ? stack[stack_ptr-1] : 0;
    assign preview1 = (stack_ptr > 1) ? stack[stack_ptr-2] : 0;

endmodule

Stack_tb.v
`timescale 1 ns / 10 ps
`define DUMPSTR(x) `"Stack_tb.vcd`"

module Stack_tb ();

    localparam WIDTH = 16;

    reg clk = 0;
    reg push_sig = 0;
    reg [2:0] pop_sig = 0;
    reg [WIDTH:0] stack_in = 0;
    wire [WIDTH:0] stack_preview0;
    wire [WIDTH:0] stack_preview1;

    // generate 12 MHz clock signal (period = 83.33 ns)
    localparam CLK_PERIOD = 83.33;
    always begin
        #(CLK_PERIOD / 2) clk <= ~clk;
    end

    // run simulation
    initial begin
        $dumpfile(`DUMPSTR(`VCD_OUTPUT));
        $dumpvars(0, Stack_tb);

        // Test 1 - read from the stack and assert zero
        #(CLK_PERIOD)

        if (stack_preview0 !== 0) begin
            $display("Test 1 failed: stack_preview0 != 0, = %d", stack_preview0);
            // $fatal;
        end

        if (stack_preview1 !== 0) begin
            $display("Test 1 failed: stack_preview1 != 0, = %d", stack_preview1);
            // $fatal;
        end

        // Test 2 - push three values onto the stack and read the top two values
        push_sig <= 1;
        stack_in <= 1;
        #(CLK_PERIOD) push_sig <= 0;
        #(CLK_PERIOD) push_sig <= 1;
        stack_in <= 2;
        #(CLK_PERIOD) push_sig <= 0;
        #(CLK_PERIOD) push_sig <= 1;
        stack_in <= 3;
        #(CLK_PERIOD) push_sig <= 0;
        #(CLK_PERIOD)

        if (stack_preview0 !== 3) begin
            $display("Test 2 failed: stack_preview0 != 3, = %d", stack_preview0);
            // $fatal;
        end

        if (stack_preview1 !== 2) begin
            $display("Test 2 failed: stack_preview1 != 2, = %d", stack_preview1);
            // $fatal;
        end

        // Test 3 - pop the top value from the stack and read the top two values
        push_sig <= 0;
        pop_sig  <= 1;
        #(CLK_PERIOD) pop_sig <= 0;
        #(CLK_PERIOD)

        if (stack_preview0 !== 2) begin
            $display("Test 3 failed: stack_preview0 != 2, = %d", stack_preview0);
            // $fatal;
        end

        if (stack_preview1 !== 1) begin
            $display("Test 3 failed: stack_preview1 != 1, = %d", stack_preview1);
            // $fatal;
        end

        // Test 4 - pop remaining two values from the stack and read the top two values
        pop_sig <= 2;
        #(CLK_PERIOD) pop_sig <= 0;
        #(CLK_PERIOD)

        if (stack_preview0 !== 0) begin
            $display("Test 4 failed: stack_preview0 != 0, = %d", stack_preview0);
            // $fatal;
        end

        if (stack_preview1 !== 0) begin
            $display("Test 4 failed: stack_preview1 != 0, = %d", stack_preview1);
            // $fatal;
        end

        // Tests complete
        #(10 * CLK_PERIOD) $display("Finished!");
        $finish;
    end

    Stack #(
        .DEPTH(127),
        .WIDTH(WIDTH)
    ) stack (
        .clk(clk),
        .push(push_sig),
        .pop(pop_sig),
        .push_data(stack_in),
        .preview0(stack_preview0),
        .preview1(stack_preview1)
    );

endmodule

Stack_tb.vcd
$date
	Sun Jul 14 14:23:13 2024
$end
$version
	Icarus Verilog
$end
$timescale
	1ps
$end
$scope module Stack_tb $end
$var wire 17 ! stack_preview1 [16:0] $end
$var wire 17 " stack_preview0 [16:0] $end
$var real 1 # CLK_PERIOD $end
$var parameter 32 $ WIDTH $end
$var reg 1 % clk $end
$var reg 3 & pop_sig [2:0] $end
$var reg 1 ' push_sig $end
$var reg 17 ( stack_in [16:0] $end
$scope module stack $end
$var wire 1 % clk $end
$var wire 3 ) pop [2:0] $end
$var wire 1 ' push $end
$var wire 17 * push_data [16:0] $end
$var wire 17 + preview1 [16:0] $end
$var wire 17 , preview0 [16:0] $end
$var parameter 32 - DEPTH $end
$var parameter 32 . WIDTH $end
$var reg 8 / stack_ptr [7:0] $end
$upscope $end
$upscope $end
$enddefinitions $end
$comment Show the parameter values. $end
$dumpall
b10000 .
b1111111 -
b10000 $
r83.33 #
$end
#0
$dumpvars
b0 /
b0 ,
b0 +
b0 *
b0 )
b0 (
0'
b0 &
0%
b0 "
b0 !
$end
#41670
1%
#83330
b1 (
b1 *
1'
#83340
0%
#125010
b1 "
b1 ,
b1 /
1%
#166660
0'
#166680
0%
#208350
1%
#249990
b10 (
b10 *
1'
#250020
0%
#291690
b10 "
b10 ,
b1 !
b1 +
b10 /
1%
#333320
0'
#333360
0%
#375030
1%
#416650
b11 (
b11 *
1'
#416700
0%
#458370
b11 "
b11 ,
b10 !
b10 +
b11 /
1%
#499980
0'
#500040
0%
#541710
1%
#583310
b1 &
b1 )
#583380
0%
#625050
b10 "
b10 ,
b1 !
b1 +
b10 /
1%
#666640
b0 &
b0 )
#666720
0%
#708390
1%
#749970
b10 &
b10 )
#750060
0%
#791730
b0 "
b0 ,
b0 !
b0 +
b0 /
1%
#833300
b0 &
b0 )
